<?xml version="1.0" encoding="utf-8" ?>
<!--가독성을 위해 dataPacket을 제일 위부터 쓰기!!-->
<PDL>
	<!--DataPackets-->
	<dataPacket name ="VectorPacket">
		<float name="x"/>
		<float name="y"/>
		<float name="z"/>
	</dataPacket>
	
	<dataPacket name ="QuaternionPacket">
		<float name="x"/>
		<float name="y"/>
		<float name="z"/>
		<float name="w"/>
	</dataPacket>
	
	<dataPacket name="RoomInfoPacket">
		<int name ="roomId"/>
		<int name ="maxCount"/>
		<int name ="currentCount"/>
		<string name="roomName"/>
	</dataPacket>
	
	<dataPacket name="PlayerInfoPacket">
		<int name="index"/>
		<bool name="isAiming"/>
		<int name="Health"/>
	</dataPacket>
	<dataPacket name="PlayerNamePacket">
		<string name ="nickName"/>
		<int name="index"/>
	</dataPacket>
	
	<dataPacket name="LocationInfoPacket">
		<int name="index"/>
		<int name="animHash"/>
		<VectorPacket name="position"/>
		<QuaternionPacket name="rotation"/>
		<QuaternionPacket name="gunRotation"/>
	</dataPacket>

	<dataPacket name="SnapshotPacket">
		<int name="index"/>
		<int name="animHash"/>
		<long name="timestamp"/>
		<VectorPacket name="position"/>
		<QuaternionPacket name="rotation"/>
		<QuaternionPacket name="gunRotation"/>
	</dataPacket>
	
	<dataPacket name ="TeamInfoPacket">
		<int name="index"/>
		<ushort name="team"/>
	</dataPacket>

	<dataPacket name="AttackInfoBr">
		<int name="hitObjIndex"/>
		<int name="attackerIndex"/>
		<bool name="isDead"/>
		<ushort name="objectType"/>
		<VectorPacket name="firePos"/>
		<VectorPacket name="direction"/>
	</dataPacket>
	<dataPacket name="CubeInfo">
		<ushort name="objectType"/>
		<int name="index"/>
		<VectorPacket name="position"/>
		<QuaternionPacket name="rotation"/>
		<VectorPacket name="size"/>
	</dataPacket>

	<dataPacket name="PlantAreaInfo">
		<ushort name="area"/>
		<CubeInfo name="cube"/>
	</dataPacket>
	<dataPacket name="DoorInfo">
		<ushort name="status"/>
		<CubeInfo name="cube"/>
	</dataPacket>
	<dataPacket name="BreakableWallInfo">
		<int name="Health"/>
		<CubeInfo name="cube"/>
	</dataPacket>
	
	<!--Packets-->
	<packet name="C_RoomEnter">
		<int name ="roomId"/>
	</packet>
	
	<packet name="S_RoomEnter">
		<PlayerNamePacket name="playerName"/>
		<LocationInfoPacket name="newPlayer"/>
	</packet>
	
	<packet name="C_RoomExit">
	</packet>
	
	<packet name="S_RoomExit">
		<int name="Index"/>
	</packet>
	
	<packet name="C_CreateRoom">
		<string name="roomName"/>
		<ushort name="playerCount"/>
		<ushort name="roundCount"/>
		<ushort name="playTime"/>
		<ushort name="bombTime"/>
	</packet>
	<packet name ="S_RoomList">
		<list name ="roomInfos">
			<roomInfoPacket name ="att"/>
		</list>
	</packet>
	<packet name="S_PacketResponse">
		<ushort name="responsePacket"/>
		<bool name="success"/>
	</packet>
	<packet name ="C_RoomList">
	</packet>
	
	<packet name="S_TestText">
		<string name="text"/>
	</packet>
	
	<packet name ="S_EnterRoomFirst">
		<int name="myIndex"/>
		<list name="playerLocations">
			<locationInfoPacket name="att"/>
		</list>
		<list name="playerNames">
			<playerNamePacket name="att"/>
		</list>
	</packet>

	<packet name="S_UpdateInfos">
		<list name="playerInfos">
			<playerInfoPacket name="att"/>
		</list>
		<list name="snapshots">
			<snapshotPacket name="att"/>
		</list>
		<list name="attacks">
			<attackInfoBr name="att"/>
		</list>
	</packet>
	<packet name="C_UpdateLocation">
		<bool name="isAiming"/>
		<LocationInfoPacket name="location"/>
	</packet>
	<packet name="S_TeamInfos">
		<list name="teamInfos">
			<teamInfoPacket name="att"/>
		</list>
	</packet>
	<packet name="S_UpdateLocations">
		<list name="locations">
			<locationInfoPacket name="att"/>
		</list>
	</packet>
	<packet name="S_SyncTimer">
		<float name="time"/>
	</packet>
	<packet name="S_UpdateRoomState">
		<ushort name="state"/>
	</packet>
	<packet name="C_ShootReq">
		<int name="hitObjIndex"/>
		<VectorPacket name="firePos"/>
		<VectorPacket name="direction"/>
	</packet>
	<packet name="S_RoundEnd">
		<int name="redCount"/>
		<int name="blueCount"/>
		<bool name="isEnd"/>
		<ushort name="winner"/>
	</packet>
	<packet name="S_GameEnd">
		<ushort name="winner"/>
	</packet>
	<packet name="C_PlantBomb">
		<ushort name="area"/>
	</packet>
	<packet name="C_DefuseBomb">
	</packet>
	<packet name="S_InitializeObjects">
		<list name="plantAreas">
			<PlantAreaInfo name="att"/>
		</list>
		<list name="doors">
			<DoorInfo name="att"/>
		</list>
		<list name="breakableWalls">
			<BreakableWallInfo name="att"/>
		</list>
	</packet>
	<packet name="S_CreateBombArea">
		<CubeInfo name="bombInfo"/>
	</packet>
	<packet name="S_SwitchRole">
		<ushort name="Attacker"/>
		<ushort name="Defender"/>
	</packet>
	<packet name="S_RemoveObject">
		<int name="index"/>
	</packet>
	<packet name="S_DoorStatus">
		<int name="index"/>
		<ushort name="status"/>
	</packet>
	<packet name="C_DoorStatus">
		<int name="index"/>
		<ushort name="status"/>
	</packet>
	<packet name="C_SetName">
		<string name="nickName"/>
	</packet>
	<packet name="S_LeaveRoom">
	</packet>
	<packet name="C_Reload">
	</packet>
	<packet name="S_Reload">
		<int name="index"/>
	</packet>
	<packet name="S_BroadcastTime">
		<long name="time"/>
	</packet>
</PDL>